zeromq_router/__init__.py
zeromq_router/exceptions/BaseException.py
zeromq_router/exceptions/InvalidHandlerException.py
zeromq_router/exceptions/NotFoundException.py
zeromq_router/servers/AsyncZMQServer.py
zeromq_router/servers/BaseZQMServer.py
zeromq_router/servers/ZMQServer.py
zeromq_router/utils/RequestContext.py
zeromq_router/utils/index.py
zeromq_router-0.1.2.dist-info/WHEEL
zeromq_router-0.1.2.dist-info/entry_points.txt
zeromq_router-0.1.2.dist-info/METADATA
zeromq_router-0.1.2.dist-info/RECORD
