Metadata-Version: 2.3
Name: zeromq-router
Version: 0.1.2
Summary: A package that provide router based endpoint for applications using ZeroMQ
Author: Obisike Treasure
Author-email: Obisike Treasure <obisiket@yahoo.com>
Requires-Dist: pyzmq>=27.1.0
Requires-Python: >=3.13
